gh_find_code_mcp/__init__.py
gh_find_code_mcp/main.py
gh_find_code_mcp-1.0.0.dist-info/METADATA
gh_find_code_mcp-1.0.0.dist-info/WHEEL
gh_find_code_mcp-1.0.0.dist-info/entry_points.txt
gh_find_code_mcp-1.0.0.dist-info/top_level.txt
gh_find_code_mcp-1.0.0.dist-info/RECORD
