Metadata-Version: 2.4
Name: gh-find-code-mcp
Version: 1.0.0
Summary: An MCP server to find code on GitHub via gh search repos
Author-email: talwrii <talwrii@gmail.com>
Project-URL: Homepage, https://github.com/talwrii/gh-find-code-mcp
Project-URL: Repository, https://github.com/talwrii/gh-find-code-mcp
Keywords: mcp,mcp-server,github,search,code-search
Classifier: Development Status :: 3 - Alpha
Classifier: License :: OSI Approved :: MIT License
Classifier: Programming Language :: Python :: 3
Requires-Python: >=3.10
Requires-Dist: mcp
